geoguessr/__init__.py
geoguessr/geoguessr.py
geoguessr/py.typed
geoguessr/util.py
geoguessr-0.0.2.dist-info/LICENSE
geoguessr-0.0.2.dist-info/METADATA
geoguessr-0.0.2.dist-info/WHEEL
geoguessr-0.0.2.dist-info/top_level.txt
geoguessr-0.0.2.dist-info/RECORD
