Metadata-Version: 2.1
Name: geoguessr
Version: 0.0.2
Summary: 3rd party API for accessing Geoguessr challenge scores
Home-page: https://github.com/jaceiverson/geoguessr
Author: Jace Iverson
License: MIT
Project-URL: Bug Tracker, https://github.com/jaceiverson/geoguessr/issues
Platform: unix
Platform: linux
Platform: osx
Platform: cygwin
Platform: win32
Classifier: Programming Language :: Python :: 3
Requires-Python: >=3.8
Provides-Extra: testing
License-File: LICENSE
